MinPackage/__init__.py
MinPackage/add.py
minpackage-1.0.0.dist-info/METADATA
minpackage-1.0.0.dist-info/WHEEL
minpackage-1.0.0.dist-info/top_level.txt
minpackage-1.0.0.dist-info/RECORD
