Metadata-Version: 2.4
Name: MinPackage
Version: 1.0.0
Summary: A simple package to add two numbers By ABU T...
Author-email: ABU Taher <tahersumonabu@gmail.com>
License: MIT
Requires-Python: >=3.7
